py_auth_micro/__init__.py
py_auth_micro/_version.py
py_auth_micro/Config/__init__.py
py_auth_micro/Config/_appconfig.py
py_auth_micro/Config/_dbconfig.py
py_auth_micro/Config/_ldapconfig.py
py_auth_micro/Core/__init__.py
py_auth_micro/Core/_enums.py
py_auth_micro/Core/_ldap_interactions.py
py_auth_micro/Exceptions/__init__.py
py_auth_micro/LoginHandler/__init__.py
py_auth_micro/LoginHandler/_loginbaseclass.py
py_auth_micro/LoginHandler/_loginldap.py
py_auth_micro/LoginHandler/_loginlocal.py
py_auth_micro/Models/__init__.py
py_auth_micro/Models/_group.py
py_auth_micro/Models/_token.py
py_auth_micro/Models/_user.py
py_auth_micro/WorkFlows/__init__.py
py_auth_micro/WorkFlows/_groupworkflow.py
py_auth_micro/WorkFlows/_misc.py
py_auth_micro/WorkFlows/_sessionworkflow.py
py_auth_micro/WorkFlows/_userworkflow.py
py_auth_micro-0.2.4.dist-info/LICENSE
py_auth_micro-0.2.4.dist-info/METADATA
py_auth_micro-0.2.4.dist-info/WHEEL
py_auth_micro-0.2.4.dist-info/top_level.txt
py_auth_micro-0.2.4.dist-info/RECORD
