Metadata-Version: 2.2
Name: py_auth_micro
Version: 0.2.4
Summary: A wrapper around pyjwt
Home-page: https://github.com/bad-microservices/py_auth_micro
Author: Ole Hannemann
Author-email: cerberus885@gmail.com
License: MIT
Keywords: JWT
Classifier: Programming Language :: Python :: 3.0
Classifier: Programming Language :: Python :: 3.9
Classifier: License :: OSI Approved :: MIT License
Classifier: Development Status :: 3 - Alpha
Classifier: Topic :: Software Development :: Libraries :: Python Modules
Classifier: Intended Audience :: Developers
License-File: LICENSE
Requires-Dist: setuptools>=45.0
Requires-Dist: tortoise-orm[asyncmy]
Requires-Dist: bcrypt
Requires-Dist: jwt_helper>=0.0.7
